pyzwave/__init__.py
pyzwave/constants.py
pyzwave/controller.py
pyzwave/input_stream.py
pyzwave/serial_interface.py
pyzwave/serial_wrapper.py
pyzwave-1.0.1.dist-info/DESCRIPTION.rst
pyzwave-1.0.1.dist-info/METADATA
pyzwave-1.0.1.dist-info/RECORD
pyzwave-1.0.1.dist-info/WHEEL
pyzwave-1.0.1.dist-info/metadata.json
pyzwave-1.0.1.dist-info/top_level.txt
